decipher_sdk/__init__.py
decipher_sdk/decipher_sdk.py
decipher_sdk-0.0.18.dist-info/METADATA
decipher_sdk-0.0.18.dist-info/WHEEL
decipher_sdk-0.0.18.dist-info/top_level.txt
decipher_sdk-0.0.18.dist-info/RECORD
