Metadata-Version: 2.1
Name: decipher-sdk
Version: 0.0.18
Summary: Flask SDK for Decipher AI
Author: Decipher AI, Inc
Author-email: michael@getdecipher.com
Requires-Dist: Flask
Requires-Dist: requests
